{
  "generator-jhipster": {
    "applicationType": "monolith",
    "gitCompany": "",
    "baseName": "provencePlay",
    "packageName": "me.provence",
    "packageFolder": "me/provence",
    "serverPort": 8080,
    "serviceDiscoveryType": false,
    "authenticationType": "jwt",
    "uaaBaseName": "../uaa",
    "cacheProvider": "ehcache",
    "enableHibernateCache": true,
    "websocket": false,
    "databaseType": "sql",
    "devDatabaseType": "h2Disk",
    "prodDatabaseType": "mysql",
    "searchEngine": false,
    "enableSwaggerCodegen": "true",
    "messageBroker": false,
    "buildTool": "maven",
    "useSass": true,
    "clientPackageManager": "npm",
    "testFrameworks": ["gatling"],
    "enableTranslation": true,
    "nativeLanguage": "en",
    "languages": ["en"],
    "clientFramework": "react",
    "jhiPrefix": "jhi",
    "jhipsterVersion": "6.9.1",
    "jwtSecretKey": "MDZkNzUwMDEyMjVlNjRhMTQzNTU5YzNlNjJjZDQyYjg0NjI2ZTllMDZiYmZjYmU1NzA5Yjg2ODgzY2UzNmMxYWJjNmI3YTQwMjYzOGM5OWVjMjVmMTFiZjliMWEwMjU3YmY5NTlhNWUwMjdhYjUxNTJlMDhlZjg1YzA3NzUxYjQ=",
    "embeddableLaunchScript": false,
    "clientTheme": "none",
    "creationTimestamp": 1591436867062,
    "entitySuffix": "",
    "dtoSuffix": "DTO",
    "otherModules": [],
    "blueprints": [],
    "prettierJava": true
  },
  "git-provider": "GitHub",
  "git-company": "ideaalloc",
  "repository-name": "provence-play"
}
